Metadata-Version: 1.0
Name: metoffice-datahub
Version: 0.5.1
Summary: MetOffice DataHub Library
Home-page: UNKNOWN
Author: bfayers
Author-email: UNKNOWN
License: GPLv3
Platform: UNKNOWN
